odoo/addons/account_payment_batch_oca_reconcile/README.rst
odoo/addons/account_payment_batch_oca_reconcile/__init__.py
odoo/addons/account_payment_batch_oca_reconcile/__manifest__.py
odoo/addons/account_payment_batch_oca_reconcile/i18n/account_payment_batch_oca_reconcile.pot
odoo/addons/account_payment_batch_oca_reconcile/i18n/fr.po
odoo/addons/account_payment_batch_oca_reconcile/i18n/it.po
odoo/addons/account_payment_batch_oca_reconcile/models/__init__.py
odoo/addons/account_payment_batch_oca_reconcile/models/account_bank_statement_line.py
odoo/addons/account_payment_batch_oca_reconcile/models/account_payment_lot.py
odoo/addons/account_payment_batch_oca_reconcile/readme/CONTRIBUTORS.md
odoo/addons/account_payment_batch_oca_reconcile/readme/DESCRIPTION.md
odoo/addons/account_payment_batch_oca_reconcile/static/description/icon.png
odoo/addons/account_payment_batch_oca_reconcile/static/description/index.html
odoo/addons/account_payment_batch_oca_reconcile/static/description/reconcile_payment_lot.png
odoo/addons/account_payment_batch_oca_reconcile/tests/__init__.py
odoo/addons/account_payment_batch_oca_reconcile/tests/test_account_payment_lot_reconcile.py
odoo/addons/account_payment_batch_oca_reconcile/views/account_bank_statement_line.xml
odoo/addons/account_payment_batch_oca_reconcile/views/account_payment_lot.xml
odoo_addon_account_payment_batch_oca_reconcile-18.0.1.0.0.7.dist-info/METADATA
odoo_addon_account_payment_batch_oca_reconcile-18.0.1.0.0.7.dist-info/WHEEL
odoo_addon_account_payment_batch_oca_reconcile-18.0.1.0.0.7.dist-info/top_level.txt
odoo_addon_account_payment_batch_oca_reconcile-18.0.1.0.0.7.dist-info/RECORD
