Metadata-Version: 2.1
Name: odoo-addon-account_payment_batch_oca_reconcile
Version: 18.0.1.0.0.7
Requires-Python: >=3.10
Requires-Dist: odoo-addon-account_payment_batch_oca==18.0.*
Requires-Dist: odoo-addon-account_reconcile_oca==18.0.*
Requires-Dist: odoo==18.0.*
Summary: Easy reconciliation of payment/debit lots on bank statement reconcile interface
Home-page: https://github.com/OCA/bank-payment-alternative
License: AGPL-3
Author: Dixmit,Akretion,Odoo Community Association (OCA)
Author-email: support@odoo-community.org
Classifier: Programming Language :: Python
Classifier: Framework :: Odoo
Classifier: Framework :: Odoo :: 18.0
Classifier: License :: OSI Approved :: GNU Affero General Public License v3
Classifier: Development Status :: 4 - Beta
